AUTHORS
LICENSE
MANIFEST.in
README.rst
setup.py
analytics/__init__.py
analytics/admin.py
analytics/basemetric.py
analytics/calculator.py
analytics/csv_views.py
analytics/geckoboard_views.py
analytics/maintenance.py
analytics/mod_analytics.py
analytics/models.py
analytics/settings.py
analytics/tests.py
analytics/urls.py
analytics/views.py
analytics/management/__init__.py
analytics/management/commands/__init__.py
analytics/management/commands/metrics.py
django_analytics.egg-info/PKG-INFO
django_analytics.egg-info/SOURCES.txt
django_analytics.egg-info/dependency_links.txt
django_analytics.egg-info/not-zip-safe
django_analytics.egg-info/requires.txt
django_analytics.egg-info/top_level.txt