Metadata-Version: 1.0
Name: django-analytics
Version: 0.0.1
Summary: Django app facilitating tracking of arbitrary simple metrics.
Home-page: https://github.com/praekelt/django-analytics
Author: Praekelt Foundation
Author-email: dev@praekelt.com
License: BSD
Platform: UNKNOWN
Classifier: Programming Language :: Python
Classifier: License :: OSI Approved :: BSD License
Classifier: Development Status :: 4 - Beta
Classifier: Operating System :: OS Independent
Classifier: Framework :: Django
Classifier: Intended Audience :: Developers
Classifier: Topic :: Internet :: WWW/HTTP :: Dynamic Content
